{
  "project_info": {
    "project_number": "708092001241",
    "project_id": "sparkchat-803a5",
    "storage_bucket": "sparkchat-803a5.appspot.com"
  },
  "client": [
    {
      "client_info": {
        "mobilesdk_app_id": "1:708092001241:android:4c3d3ce4910eba8a5cf7c8",
        "android_client_info": {
          "package_name": "com.example.spark_chat"
        }
      },
      "oauth_client": [],
      "api_key": [
        {
          "current_key": "AIzaSyCvoQB7a57GDj0hqBfNOYONDX0qU2mdW0c"
        }
      ],
      "services": {
        "appinvite_service": {
          "other_platform_oauth_client": []
        }
      }
    }
  ],
  "configuration_version": "1"
}